{
  "parent": "minecraft:block/block",
  "elements": [
    {
      "faces": {
        "down": {
          "texture": "#top",
          "tintindex": 0
        },
        "east": {
          "texture": "#side",
          "tintindex": 0
        },
        "north": {
          "texture": "#side",
          "tintindex": 0
        },
        "south": {
          "texture": "#side",
          "tintindex": 0
        },
        "up": {
          "texture": "#top",
          "tintindex": 0
        },
        "west": {
          "texture": "#side",
          "tintindex": 0
        }
      },
      "from": [
        4,
        0,
        4
      ],
      "to": [
        12,
        2,
        12
      ]
    },
    {
      "faces": {
        "up": {
          "texture": "#overlay",
          "tintindex": 1
        }
      },
      "from": [
        4,
        0,
        4
      ],
      "to": [
        12,
        2,
        12
      ]
    }
  ],
  "render_type": "minecraft:cutout",
  "textures": {
    "overlay": "trofers:block/small_plate_overlay",
    "particle": "#top",
    "side": "trofers:block/small_pillar_side",
    "top": "trofers:block/small_pillar_top"
  }
}