{
  "colors": {
    "accent": "#AE8A63",
    "base": "#606060"
  },
  "conditions": [
    {
      "type": "forge:mod_loaded",
      "modid": "alexsmobs"
    }
  ],
  "display": {
    "scale": 0.25
  },
  "effects": {
    "rewards": {
      "cooldown": 9600,
      "lootTable": "trofers:trophies/alexsmobs/gelada_monkey"
    },
    "sound": {
      "soundEvent": "alexsmobs:gelada_monkey_idle"
    }
  },
  "entity": {
    "type": "alexsmobs:gelada_monkey"
  },
  "name": {
    "color": "#AE8A63",
    "translate": "trophy.trofers.composed",
    "with": [
      {
        "translate": "entity.alexsmobs.gelada_monkey"
      }
    ]
  }
}